read_in_terminal/__init__.py
read_in_terminal/controller.py
read_in_terminal/main.py
read_in_terminal/utils.py
read_in_terminal-1.0.0.dist-info/LICENSE
read_in_terminal-1.0.0.dist-info/METADATA
read_in_terminal-1.0.0.dist-info/WHEEL
read_in_terminal-1.0.0.dist-info/entry_points.txt
read_in_terminal-1.0.0.dist-info/top_level.txt
read_in_terminal-1.0.0.dist-info/RECORD
